{
  "cpuTime": 0.013136000372469425,
  "envs": {
    "bytes": 53232,
    "elements": 4291,
    "number": 2363
  },
  "gc": {
    "heapSize": 402915328,
    "totalBytes": 289056
  },
  "list": {
    "bytes": 3976,
    "concats": 68,
    "elements": 497
  },
  "nrAvoided": 2527,
  "nrFunctionCalls": 1913,
  "nrLookups": 1602,
  "nrOpUpdateValuesCopied": 1557,
  "nrOpUpdates": 190,
  "nrPrimOpCalls": 958,
  "nrThunks": 4258,
  "sets": {
    "bytes": 82088,
    "elements": 4735,
    "number": 791
  },
  "sizes": {
    "Attr": 16,
    "Bindings": 8,
    "Env": 8,
    "Value": 8
  },
  "symbols": {
    "bytes": 12971,
    "number": 1339
  },
  "values": {
    "bytes": 0,
    "number": 0
  }
}
